{
    "obtainedMarks": {},
    "otherActivityMarks": {
        "lessThan": {
            "fieldName": "obtainedMarks"
        }
    },
    "passingMarks": {
        "lessThan": {
            "fieldName": "obtainedMarks",
            "conditionalExpression": "x => x.obtainedMarks < 35"
        }
    },
    "otherMarks": {
        "lessThan": {
            "fieldName": "obtainedMarks",
            "message": "Please enter number which is less than above field input."
        }
    },
    "disciplineMarks": {
        "lessThan": {
            "fieldName": "obtainedMarks",
            "messageKey": "lessThanMessageKey"
        }
    }
}